LICENSE
MANIFEST.in
README.rst
Readme.md
pyproject.toml
setup.cfg
setup.py
django_introspectmodels.egg-info/PKG-INFO
django_introspectmodels.egg-info/SOURCES.txt
django_introspectmodels.egg-info/dependency_links.txt
django_introspectmodels.egg-info/requires.txt
django_introspectmodels.egg-info/top_level.txt
introspectmodels/__init__.py
introspectmodels/apps.py
introspectmodels/tests.py
introspectmodels/introspect_utils/__init__.py
introspectmodels/introspect_utils/models_introspector.py
introspectmodels/management/__init__.py
introspectmodels/management/commands/__init__.py
introspectmodels/management/commands/introspectmodels.py